{
    "CurrencyIsoCode": "USD",
    "IsActive": true,
    "IsLocked": false,
    "IsOmniScriptEmbeddable": false,
    "MayEdit": true,
    "Name": "CreateContentDocumentLinksForResume",
    "OmniProcessId": {
        "Name": "CreateApplicationFormAndRelatedRecords",
        "VlocityDataPackType": "VlocityMatchingKeyObject",
        "VlocityMatchingRecordSourceKey": "OmniProcess/Recruitment/CreateApplicationFormAndRelatedRecords/Procedure",
        "VlocityRecordSObjectType": "OmniProcess"
    },
    "ParentElementId": {
        "Name": "LoopOverResume",
        "OmniProcessId": {
            "Name": "CreateApplicationFormAndRelatedRecords",
            "VlocityDataPackType": "VlocityMatchingKeyObject",
            "VlocityMatchingRecordSourceKey": "OmniProcess/Recruitment/CreateApplicationFormAndRelatedRecords/Procedure",
            "VlocityRecordSObjectType": "OmniProcess"
        },
        "VlocityDataPackType": "VlocityMatchingKeyObject",
        "VlocityMatchingRecordSourceKey": "OmniProcessElement/OmniProcess/Recruitment/CreateApplicationFormAndRelatedRecords/Procedure/LoopOverResume",
        "VlocityRecordSObjectType": "OmniProcessElement"
    },
    "ParentElementName": "LoopOverResume",
    "ParentElementType": "Loop Block",
    "PropertySetConfig": {
        "actionMessage": "",
        "additionalInput": {
            "File:data": "%Resume:data%",
            "LinkedEntityId": "%applicationFormId%"
        },
        "additionalOutput": {
        },
        "bundle": "RecruitmentCreateContentDocumentLinks",
        "chainOnStep": false,
        "disOnTplt": false,
        "executionConditionalFormula": "",
        "failOnStepError": true,
        "failureConditionalFormula": "",
        "failureResponse": {
        },
        "label": "DataMapperPostAction5",
        "responseJSONNode": "",
        "responseJSONPath": "",
        "returnOnlyAdditionalOutput": false,
        "returnOnlyFailureResponse": false,
        "sendJSONNode": "",
        "sendJSONPath": "",
        "sendOnlyAdditionalInput": true,
        "show": null,
        "useFormulas": true
    },
    "Type": "DataRaptor Post Action",
    "VlocityDataPackType": "SObject",
    "VlocityRecordSObjectType": "OmniProcessElement",
    "VlocityRecordSourceKey": "OmniProcessElement/OmniProcess/Recruitment/CreateApplicationFormAndRelatedRecords/Procedure/CreateContentDocumentLinksForResume"
}