{
    "UploadDocuments": {
        "EducationDocuments": [
            {
                "PersonEducationId": "0Srxx0000004EUCCA2",
                "UploadDegree": "1 file",
                "UploadInstitution": "1 file hjbasdjh"
            },
            {
                "PersonEducationId": "0Srxx0000004EVoCAM",
                "UploadDegree": "no file",
                "UploadInstitution": "no file"
            },
            {
                "PersonEducationId": "0Srxx0000004EXQCA2",
                "UploadDegree": "2 file",
                "UploadInstitution": "2 file"
            }
        ]
    }
}