[
    {
        "CurrencyIsoCode": "USD",
        "GlobalKey": "FCCreateCourseParticipant4530019262110645",
        "InputFieldName": "ApplicationId",
        "IsDisabled": false,
        "IsLocked": false,
        "IsRequiredForUpsert": false,
        "IsUpsertKey": false,
        "MayEdit": true,
        "Name": "FCCreateCourseParticipant",
        "OmniDataTransformationId": {
            "Name": "FCCreateCourseParticipant",
            "VlocityDataPackType": "VlocityMatchingKeyObject",
            "VlocityMatchingRecordSourceKey": "OmniDataTransform/FCCreateCourseParticipant",
            "VlocityRecordSObjectType": "OmniDataTransform"
        },
        "OutputCreationSequence": 1,
        "OutputFieldName": "Application__c",
        "OutputObjectName": "TrainingCourseParticipant",
        "VlocityDataPackType": "SObject",
        "VlocityRecordSObjectType": "OmniDataTransformItem"
    },
    {
        "CurrencyIsoCode": "USD",
        "GlobalKey": "FCCreateCourseParticipant3609861241534311",
        "InputFieldName": "ContactId",
        "IsDisabled": false,
        "IsLocked": false,
        "IsRequiredForUpsert": false,
        "IsUpsertKey": false,
        "MayEdit": true,
        "Name": "FCCreateCourseParticipant",
        "OmniDataTransformationId": {
            "Name": "FCCreateCourseParticipant",
            "VlocityDataPackType": "VlocityMatchingKeyObject",
            "VlocityMatchingRecordSourceKey": "OmniDataTransform/FCCreateCourseParticipant",
            "VlocityRecordSObjectType": "OmniDataTransform"
        },
        "OutputCreationSequence": 1,
        "OutputFieldName": "ContactId",
        "OutputObjectName": "TrainingCourseParticipant",
        "VlocityDataPackType": "SObject",
        "VlocityRecordSObjectType": "OmniDataTransformItem"
    },
    {
        "CurrencyIsoCode": "USD",
        "GlobalKey": "FCCreateCourseParticipant9772975247729323",
        "InputFieldName": "Select:TrainingOffering",
        "IsDisabled": false,
        "IsLocked": false,
        "IsRequiredForUpsert": false,
        "IsUpsertKey": false,
        "LookupByFieldName": "Course_Id__c",
        "LookupObjectName": "CourseOffering",
        "LookupReturnedFieldName": "Id",
        "MayEdit": true,
        "Name": "FCCreateCourseParticipant",
        "OmniDataTransformationId": {
            "Name": "FCCreateCourseParticipant",
            "VlocityDataPackType": "VlocityMatchingKeyObject",
            "VlocityMatchingRecordSourceKey": "OmniDataTransform/FCCreateCourseParticipant",
            "VlocityRecordSObjectType": "OmniDataTransform"
        },
        "OutputCreationSequence": 1,
        "OutputFieldName": "CourseOfferingId",
        "OutputObjectName": "TrainingCourseParticipant",
        "VlocityDataPackType": "SObject",
        "VlocityRecordSObjectType": "OmniDataTransformItem"
    },
    {
        "CurrencyIsoCode": "USD",
        "FilterOperator": "=",
        "GlobalKey": "FCCreateCourseParticipant22400491295017932",
        "IsDisabled": true,
        "IsLocked": false,
        "IsRequiredForUpsert": false,
        "IsUpsertKey": false,
        "MayEdit": true,
        "MigrationValue": "FAKEMAPPING",
        "Name": "FCCreateCourseParticipant",
        "OmniDataTransformationId": {
            "Name": "FCCreateCourseParticipant",
            "VlocityDataPackType": "VlocityMatchingKeyObject",
            "VlocityMatchingRecordSourceKey": "OmniDataTransform/FCCreateCourseParticipant",
            "VlocityRecordSObjectType": "OmniDataTransform"
        },
        "OutputCreationSequence": 1,
        "OutputFieldName": "Id",
        "OutputObjectName": "TrainingCourseParticipant",
        "VlocityDataPackType": "SObject",
        "VlocityRecordSObjectType": "OmniDataTransformItem"
    },
    {
        "CurrencyIsoCode": "USD",
        "DefaultValue": "Department of Social Services",
        "GlobalKey": "FCCreateCourseParticipant16854618924736853",
        "IsDisabled": false,
        "IsLocked": false,
        "IsRequiredForUpsert": false,
        "IsUpsertKey": false,
        "MayEdit": true,
        "Name": "FCCreateCourseParticipant",
        "OmniDataTransformationId": {
            "Name": "FCCreateCourseParticipant",
            "VlocityDataPackType": "VlocityMatchingKeyObject",
            "VlocityMatchingRecordSourceKey": "OmniDataTransform/FCCreateCourseParticipant",
            "VlocityRecordSObjectType": "OmniDataTransform"
        },
        "OutputCreationSequence": 1,
        "OutputFieldName": "InstitutionName",
        "OutputObjectName": "TrainingCourseParticipant",
        "VlocityDataPackType": "SObject",
        "VlocityRecordSObjectType": "OmniDataTransformItem"
    },
    {
        "CurrencyIsoCode": "USD",
        "GlobalKey": "FCCreateCourseParticipant2197716972352428",
        "InputFieldName": "Select:TrainingOffering",
        "IsDisabled": false,
        "IsLocked": false,
        "IsRequiredForUpsert": false,
        "IsUpsertKey": false,
        "LookupByFieldName": "Course_Id__c",
        "LookupObjectName": "CourseOffering",
        "LookupReturnedFieldName": "StartDate",
        "MayEdit": true,
        "Name": "FCCreateCourseParticipant",
        "OmniDataTransformationId": {
            "Name": "FCCreateCourseParticipant",
            "VlocityDataPackType": "VlocityMatchingKeyObject",
            "VlocityMatchingRecordSourceKey": "OmniDataTransform/FCCreateCourseParticipant",
            "VlocityRecordSObjectType": "OmniDataTransform"
        },
        "OutputCreationSequence": 1,
        "OutputFieldName": "StartDate",
        "OutputObjectName": "TrainingCourseParticipant",
        "VlocityDataPackType": "SObject",
        "VlocityRecordSObjectType": "OmniDataTransformItem"
    },
    {
        "CurrencyIsoCode": "USD",
        "GlobalKey": "FCCreateCourseParticipant8130449965912931",
        "InputFieldName": "TotalHours",
        "IsDisabled": false,
        "IsLocked": false,
        "IsRequiredForUpsert": false,
        "IsUpsertKey": false,
        "MayEdit": true,
        "Name": "FCCreateCourseParticipant",
        "OmniDataTransformationId": {
            "Name": "FCCreateCourseParticipant",
            "VlocityDataPackType": "VlocityMatchingKeyObject",
            "VlocityMatchingRecordSourceKey": "OmniDataTransform/FCCreateCourseParticipant",
            "VlocityRecordSObjectType": "OmniDataTransform"
        },
        "OutputCreationSequence": 1,
        "OutputFieldName": "TotalHours",
        "OutputObjectName": "TrainingCourseParticipant",
        "VlocityDataPackType": "SObject",
        "VlocityRecordSObjectType": "OmniDataTransformItem"
    }
]