{
    "CurrencyIsoCode": "USD",
    "IsActive": true,
    "IsLocked": false,
    "IsOmniScriptEmbeddable": false,
    "MayEdit": true,
    "Name": "ReviewerTypeIncident",
    "OmniProcessId": {
        "Name": "New Visit Generic",
        "VlocityDataPackType": "VlocityMatchingKeyObject",
        "VlocityMatchingRecordSourceKey": "OmniProcess/LPI/NewVisit/English",
        "VlocityRecordSObjectType": "OmniProcess"
    },
    "ParentElementId": {
        "Name": "VisitDetails",
        "OmniProcessId": {
            "Name": "New Visit Generic",
            "VlocityDataPackType": "VlocityMatchingKeyObject",
            "VlocityMatchingRecordSourceKey": "OmniProcess/LPI/NewVisit/English",
            "VlocityRecordSObjectType": "OmniProcess"
        },
        "VlocityDataPackType": "VlocityMatchingKeyObject",
        "VlocityMatchingRecordSourceKey": "OmniProcessElement/OmniProcess/LPI/NewVisit/English/VisitDetails",
        "VlocityRecordSObjectType": "OmniProcessElement"
    },
    "ParentElementName": "VisitDetails",
    "ParentElementType": "Step",
    "PropertySetConfig": {
        "HTMLTemplateId": "",
        "accessibleInFutureSteps": false,
        "conditionType": "Hide if False",
        "controlWidth": 11,
        "controllingField": {
            "element": "",
            "source": "",
            "type": ""
        },
        "defaultValue": "Case Owner",
        "disOnTplt": false,
        "enableCaption": true,
        "help": false,
        "helpText": "",
        "helpTextPos": "",
        "hide": false,
        "horizontalMode": true,
        "imageCountInRow": 3,
        "label": "Visit to be Conducted By:",
        "optionHeight": 100,
        "optionSource": {
            "source": "",
            "type": ""
        },
        "optionWidth": 100,
        "options": [
            {
                "autoAdv": null,
                "developerName": null,
                "name": "Case Owner",
                "value": "Case Owner (Note:Should have Inspection Permissions)"
            },
            {
                "autoAdv": null,
                "developerName": null,
                "name": "Other User",
                "value": "Other User"
            }
        ],
        "readOnly": false,
        "repeat": false,
        "repeatClone": false,
        "repeatLimit": null,
        "required": true,
        "show": {
            "group": {
                "operator": "AND",
                "rules": [
                    {
                        "condition": "<>",
                        "data": null,
                        "field": "InspectionTypeId"
                    },
                    {
                        "condition": "=",
                        "data": "Case",
                        "field": "InspectionType"
                    }
                ]
            }
        }
    },
    "Type": "Radio",
    "VlocityDataPackType": "SObject",
    "VlocityRecordSObjectType": "OmniProcessElement",
    "VlocityRecordSourceKey": "OmniProcessElement/OmniProcess/LPI/NewVisit/English/ReviewerTypeIncident"
}