[
    {
        "CurrencyIsoCode": "USD",
        "FilterGroup": 0,
        "FormulaExpression": "CONCAT(ApplicantInformation:FirstName,\" \",ApplicantInformation:LastName)",
        "FormulaResultPath": "PurchaserFullName",
        "FormulaSequence": 1,
        "GlobalKey": "LPIPopulateDCMPD2191869711479011853",
        "InputObjectQuerySequence": 0,
        "IsDisabled": false,
        "IsLocked": false,
        "IsRequiredForUpsert": false,
        "IsUpsertKey": false,
        "LinkedObjectSequence": 0,
        "MayEdit": true,
        "Name": "LPIPopulateDCMPD219",
        "OmniDataTransformationId": {
            "Name": "LPIPopulateDCMPD219",
            "VlocityDataPackType": "VlocityMatchingKeyObject",
            "VlocityMatchingRecordSourceKey": "OmniDataTransform/LPIPopulateDCMPD219",
            "VlocityRecordSObjectType": "OmniDataTransform"
        },
        "OutputCreationSequence": 0,
        "OutputFieldName": "Formula",
        "OutputObjectName": "Formula",
        "VlocityDataPackType": "SObject",
        "VlocityRecordSObjectType": "OmniDataTransformItem"
    },
    {
        "CurrencyIsoCode": "USD",
        "FilterGroup": 0,
        "FormulaExpression": "CONCAT(FirearmsRegistration:AddressHistory:AddressHistoryStreet,\",\",FirearmsRegistration:AddressHistory:AddressHistoryCity,\",\",FirearmsRegistration:AddressHistory:AddressHistoryState,\",\",FirearmsRegistration:AddressHistory:AddressHistoryZip,\" - \",FirearmsRegistration:AddressHistory:AddressStart,\"-\",FirearmsRegistration:AddressHistory:AddressEnd)",
        "FormulaResultPath": "PastAddress1",
        "FormulaSequence": 2,
        "GlobalKey": "LPIPopulateDCMPD2197907225274804934",
        "InputObjectQuerySequence": 0,
        "IsDisabled": false,
        "IsLocked": false,
        "IsRequiredForUpsert": false,
        "IsUpsertKey": false,
        "LinkedObjectSequence": 0,
        "MayEdit": true,
        "Name": "LPIPopulateDCMPD219",
        "OmniDataTransformationId": {
            "Name": "LPIPopulateDCMPD219",
            "VlocityDataPackType": "VlocityMatchingKeyObject",
            "VlocityMatchingRecordSourceKey": "OmniDataTransform/LPIPopulateDCMPD219",
            "VlocityRecordSObjectType": "OmniDataTransform"
        },
        "OutputCreationSequence": 0,
        "OutputFieldName": "Formula",
        "OutputObjectName": "Formula",
        "VlocityDataPackType": "SObject",
        "VlocityRecordSObjectType": "OmniDataTransformItem"
    },
    {
        "CurrencyIsoCode": "USD",
        "FilterGroup": 0,
        "FormulaExpression": "\"29392939-2939291\"",
        "FormulaResultPath": "FormulaSerialNumber",
        "FormulaSequence": 3,
        "GlobalKey": "LPIPopulateDCMPD2197048233443660956",
        "InputObjectQuerySequence": 0,
        "IsDisabled": false,
        "IsLocked": false,
        "IsRequiredForUpsert": false,
        "IsUpsertKey": false,
        "LinkedObjectSequence": 0,
        "MayEdit": true,
        "Name": "LPIPopulateDCMPD219",
        "OmniDataTransformationId": {
            "Name": "LPIPopulateDCMPD219",
            "VlocityDataPackType": "VlocityMatchingKeyObject",
            "VlocityMatchingRecordSourceKey": "OmniDataTransform/LPIPopulateDCMPD219",
            "VlocityRecordSObjectType": "OmniDataTransform"
        },
        "OutputCreationSequence": 0,
        "OutputFieldName": "Formula",
        "OutputObjectName": "Formula",
        "VlocityDataPackType": "SObject",
        "VlocityRecordSObjectType": "OmniDataTransformItem"
    },
    {
        "CurrencyIsoCode": "USD",
        "FilterGroup": 0,
        "GlobalKey": "LPIPopulateDCMPD2199872627092935389",
        "InputFieldName": "FirearmsRegistration:BarrelLength",
        "InputObjectQuerySequence": 0,
        "IsDisabled": false,
        "IsLocked": false,
        "IsRequiredForUpsert": false,
        "IsUpsertKey": false,
        "LinkedObjectSequence": 0,
        "MayEdit": true,
        "Name": "LPIPopulateDCMPD219",
        "OmniDataTransformationId": {
            "Name": "LPIPopulateDCMPD219",
            "VlocityDataPackType": "VlocityMatchingKeyObject",
            "VlocityMatchingRecordSourceKey": "OmniDataTransform/LPIPopulateDCMPD219",
            "VlocityRecordSObjectType": "OmniDataTransform"
        },
        "OutputCreationSequence": 1,
        "OutputFieldName": "BarrelLength",
        "OutputObjectName": "json",
        "VlocityDataPackType": "SObject",
        "VlocityRecordSObjectType": "OmniDataTransformItem"
    },
    {
        "CurrencyIsoCode": "USD",
        "FilterGroup": 0,
        "GlobalKey": "LPIPopulateDCMPD21939665427929843",
        "InputFieldName": "ApplicantInformation:WorkPhone",
        "InputObjectQuerySequence": 0,
        "IsDisabled": false,
        "IsLocked": false,
        "IsRequiredForUpsert": false,
        "IsUpsertKey": false,
        "LinkedObjectSequence": 0,
        "MayEdit": true,
        "Name": "LPIPopulateDCMPD219",
        "OmniDataTransformationId": {
            "Name": "LPIPopulateDCMPD219",
            "VlocityDataPackType": "VlocityMatchingKeyObject",
            "VlocityMatchingRecordSourceKey": "OmniDataTransform/LPIPopulateDCMPD219",
            "VlocityRecordSObjectType": "OmniDataTransform"
        },
        "OutputCreationSequence": 1,
        "OutputFieldName": "BusinessPhone",
        "OutputObjectName": "json",
        "VlocityDataPackType": "SObject",
        "VlocityRecordSObjectType": "OmniDataTransformItem"
    },
    {
        "CurrencyIsoCode": "USD",
        "FilterGroup": 0,
        "GlobalKey": "LPIPopulateDCMPD21907311224546741046",
        "InputFieldName": "FirearmsRegistration:Caliber",
        "InputObjectQuerySequence": 0,
        "IsDisabled": false,
        "IsLocked": false,
        "IsRequiredForUpsert": false,
        "IsUpsertKey": false,
        "LinkedObjectSequence": 0,
        "MayEdit": true,
        "Name": "LPIPopulateDCMPD219",
        "OmniDataTransformationId": {
            "Name": "LPIPopulateDCMPD219",
            "VlocityDataPackType": "VlocityMatchingKeyObject",
            "VlocityMatchingRecordSourceKey": "OmniDataTransform/LPIPopulateDCMPD219",
            "VlocityRecordSObjectType": "OmniDataTransform"
        },
        "OutputCreationSequence": 1,
        "OutputFieldName": "Caliber",
        "OutputObjectName": "json",
        "VlocityDataPackType": "SObject",
        "VlocityRecordSObjectType": "OmniDataTransformItem"
    },
    {
        "CurrencyIsoCode": "USD",
        "FilterGroup": 0,
        "GlobalKey": "LPIPopulateDCMPD2199247432438283012",
        "InputFieldName": "FirearmsRegistration:Finish",
        "InputObjectQuerySequence": 0,
        "IsDisabled": false,
        "IsLocked": false,
        "IsRequiredForUpsert": false,
        "IsUpsertKey": false,
        "LinkedObjectSequence": 0,
        "MayEdit": true,
        "Name": "LPIPopulateDCMPD219",
        "OmniDataTransformationId": {
            "Name": "LPIPopulateDCMPD219",
            "VlocityDataPackType": "VlocityMatchingKeyObject",
            "VlocityMatchingRecordSourceKey": "OmniDataTransform/LPIPopulateDCMPD219",
            "VlocityRecordSObjectType": "OmniDataTransform"
        },
        "OutputCreationSequence": 1,
        "OutputFieldName": "Finish",
        "OutputObjectName": "json",
        "VlocityDataPackType": "SObject",
        "VlocityRecordSObjectType": "OmniDataTransformItem"
    },
    {
        "CurrencyIsoCode": "USD",
        "FilterGroup": 0,
        "GlobalKey": "LPIPopulateDCMPD2196415498071970673",
        "InputFieldName": "FirearmsRegistration:BriefStatement",
        "InputObjectQuerySequence": 0,
        "IsDisabled": false,
        "IsLocked": false,
        "IsRequiredForUpsert": false,
        "IsUpsertKey": false,
        "LinkedObjectSequence": 0,
        "MayEdit": true,
        "Name": "LPIPopulateDCMPD219",
        "OmniDataTransformationId": {
            "Name": "LPIPopulateDCMPD219",
            "VlocityDataPackType": "VlocityMatchingKeyObject",
            "VlocityMatchingRecordSourceKey": "OmniDataTransform/LPIPopulateDCMPD219",
            "VlocityRecordSObjectType": "OmniDataTransform"
        },
        "OutputCreationSequence": 1,
        "OutputFieldName": "FirearmLocation",
        "OutputObjectName": "json",
        "VlocityDataPackType": "SObject",
        "VlocityRecordSObjectType": "OmniDataTransformItem"
    },
    {
        "CurrencyIsoCode": "USD",
        "FilterGroup": 0,
        "GlobalKey": "LPIPopulateDCMPD21910111756144812967",
        "InputFieldName": "ApplicantInformation:HomePhone",
        "InputObjectQuerySequence": 0,
        "IsDisabled": false,
        "IsLocked": false,
        "IsRequiredForUpsert": false,
        "IsUpsertKey": false,
        "LinkedObjectSequence": 0,
        "MayEdit": true,
        "Name": "LPIPopulateDCMPD219",
        "OmniDataTransformationId": {
            "Name": "LPIPopulateDCMPD219",
            "VlocityDataPackType": "VlocityMatchingKeyObject",
            "VlocityMatchingRecordSourceKey": "OmniDataTransform/LPIPopulateDCMPD219",
            "VlocityRecordSObjectType": "OmniDataTransform"
        },
        "OutputCreationSequence": 1,
        "OutputFieldName": "HomePhone",
        "OutputObjectName": "json",
        "VlocityDataPackType": "SObject",
        "VlocityRecordSObjectType": "OmniDataTransformItem"
    },
    {
        "CurrencyIsoCode": "USD",
        "FilterGroup": 0,
        "GlobalKey": "LPIPopulateDCMPD2192894930154053983",
        "InputFieldName": "FirearmsRegistration:IdentifyingMarks",
        "InputObjectQuerySequence": 0,
        "IsDisabled": false,
        "IsLocked": false,
        "IsRequiredForUpsert": false,
        "IsUpsertKey": false,
        "LinkedObjectSequence": 0,
        "MayEdit": true,
        "Name": "LPIPopulateDCMPD219",
        "OmniDataTransformationId": {
            "Name": "LPIPopulateDCMPD219",
            "VlocityDataPackType": "VlocityMatchingKeyObject",
            "VlocityMatchingRecordSourceKey": "OmniDataTransform/LPIPopulateDCMPD219",
            "VlocityRecordSObjectType": "OmniDataTransform"
        },
        "OutputCreationSequence": 1,
        "OutputFieldName": "IdentifyingMarks",
        "OutputObjectName": "json",
        "VlocityDataPackType": "SObject",
        "VlocityRecordSObjectType": "OmniDataTransformItem"
    },
    {
        "CurrencyIsoCode": "USD",
        "FilterGroup": 0,
        "GlobalKey": "LPIPopulateDCMPD2198020436789246419",
        "InputFieldName": "FirearmsRegistration:MakeOfWeapon",
        "InputObjectQuerySequence": 0,
        "IsDisabled": false,
        "IsLocked": false,
        "IsRequiredForUpsert": false,
        "IsUpsertKey": false,
        "LinkedObjectSequence": 0,
        "MayEdit": true,
        "Name": "LPIPopulateDCMPD219",
        "OmniDataTransformationId": {
            "Name": "LPIPopulateDCMPD219",
            "VlocityDataPackType": "VlocityMatchingKeyObject",
            "VlocityMatchingRecordSourceKey": "OmniDataTransform/LPIPopulateDCMPD219",
            "VlocityRecordSObjectType": "OmniDataTransform"
        },
        "OutputCreationSequence": 1,
        "OutputFieldName": "MakeOfWeapon",
        "OutputObjectName": "json",
        "VlocityDataPackType": "SObject",
        "VlocityRecordSObjectType": "OmniDataTransformItem"
    },
    {
        "CurrencyIsoCode": "USD",
        "FilterGroup": 0,
        "GlobalKey": "LPIPopulateDCMPD21948770174034266645",
        "InputFieldName": "FirearmsRegistration:ManufacturerIdNo",
        "InputObjectQuerySequence": 0,
        "IsDisabled": false,
        "IsLocked": false,
        "IsRequiredForUpsert": false,
        "IsUpsertKey": false,
        "LinkedObjectSequence": 0,
        "MayEdit": true,
        "Name": "LPIPopulateDCMPD219",
        "OmniDataTransformationId": {
            "Name": "LPIPopulateDCMPD219",
            "VlocityDataPackType": "VlocityMatchingKeyObject",
            "VlocityMatchingRecordSourceKey": "OmniDataTransform/LPIPopulateDCMPD219",
            "VlocityRecordSObjectType": "OmniDataTransform"
        },
        "OutputCreationSequence": 1,
        "OutputFieldName": "ManufacturerIdNo",
        "OutputObjectName": "json",
        "VlocityDataPackType": "SObject",
        "VlocityRecordSObjectType": "OmniDataTransformItem"
    },
    {
        "CurrencyIsoCode": "USD",
        "FilterGroup": 0,
        "GlobalKey": "LPIPopulateDCMPD21906712040922246043",
        "InputFieldName": "FirearmsRegistration:Model",
        "InputObjectQuerySequence": 0,
        "IsDisabled": false,
        "IsLocked": false,
        "IsRequiredForUpsert": false,
        "IsUpsertKey": false,
        "LinkedObjectSequence": 0,
        "MayEdit": true,
        "Name": "LPIPopulateDCMPD219",
        "OmniDataTransformationId": {
            "Name": "LPIPopulateDCMPD219",
            "VlocityDataPackType": "VlocityMatchingKeyObject",
            "VlocityMatchingRecordSourceKey": "OmniDataTransform/LPIPopulateDCMPD219",
            "VlocityRecordSObjectType": "OmniDataTransform"
        },
        "OutputCreationSequence": 1,
        "OutputFieldName": "Model",
        "OutputObjectName": "json",
        "VlocityDataPackType": "SObject",
        "VlocityRecordSObjectType": "OmniDataTransformItem"
    },
    {
        "CurrencyIsoCode": "USD",
        "FilterGroup": 0,
        "GlobalKey": "LPIPopulateDCMPD2197651426071679341",
        "InputFieldName": "FirearmsRegistration:NoOfShots",
        "InputObjectQuerySequence": 0,
        "IsDisabled": false,
        "IsLocked": false,
        "IsRequiredForUpsert": false,
        "IsUpsertKey": false,
        "LinkedObjectSequence": 0,
        "MayEdit": true,
        "Name": "LPIPopulateDCMPD219",
        "OmniDataTransformationId": {
            "Name": "LPIPopulateDCMPD219",
            "VlocityDataPackType": "VlocityMatchingKeyObject",
            "VlocityMatchingRecordSourceKey": "OmniDataTransform/LPIPopulateDCMPD219",
            "VlocityRecordSObjectType": "OmniDataTransform"
        },
        "OutputCreationSequence": 1,
        "OutputFieldName": "NoOfShots",
        "OutputObjectName": "json",
        "VlocityDataPackType": "SObject",
        "VlocityRecordSObjectType": "OmniDataTransformItem"
    },
    {
        "CurrencyIsoCode": "USD",
        "FilterGroup": 0,
        "GlobalKey": "LPIPopulateDCMPD2192928201868386633",
        "InputFieldName": "FirearmsRegistration:NoOfBarrels",
        "InputObjectQuerySequence": 0,
        "IsDisabled": false,
        "IsLocked": false,
        "IsRequiredForUpsert": false,
        "IsUpsertKey": false,
        "LinkedObjectSequence": 0,
        "MayEdit": true,
        "Name": "LPIPopulateDCMPD219",
        "OmniDataTransformationId": {
            "Name": "LPIPopulateDCMPD219",
            "VlocityDataPackType": "VlocityMatchingKeyObject",
            "VlocityMatchingRecordSourceKey": "OmniDataTransform/LPIPopulateDCMPD219",
            "VlocityRecordSObjectType": "OmniDataTransform"
        },
        "OutputCreationSequence": 1,
        "OutputFieldName": "NumberofBarrels",
        "OutputObjectName": "json",
        "VlocityDataPackType": "SObject",
        "VlocityRecordSObjectType": "OmniDataTransformItem"
    },
    {
        "CurrencyIsoCode": "USD",
        "FilterGroup": 0,
        "GlobalKey": "LPIPopulateDCMPD2194842427567765393",
        "InputFieldName": "ApplicantInformation:DateOfBirth",
        "InputObjectQuerySequence": 0,
        "IsDisabled": false,
        "IsLocked": false,
        "IsRequiredForUpsert": false,
        "IsUpsertKey": false,
        "LinkedObjectSequence": 0,
        "MayEdit": true,
        "Name": "LPIPopulateDCMPD219",
        "OmniDataTransformationId": {
            "Name": "LPIPopulateDCMPD219",
            "VlocityDataPackType": "VlocityMatchingKeyObject",
            "VlocityMatchingRecordSourceKey": "OmniDataTransform/LPIPopulateDCMPD219",
            "VlocityRecordSObjectType": "OmniDataTransform"
        },
        "OutputCreationSequence": 1,
        "OutputFieldName": "PurchaserDOB",
        "OutputObjectName": "json",
        "VlocityDataPackType": "SObject",
        "VlocityRecordSObjectType": "OmniDataTransformItem"
    },
    {
        "CurrencyIsoCode": "USD",
        "FilterGroup": 0,
        "GlobalKey": "LPIPopulateDCMPD2196751056356340377",
        "InputFieldName": "ApplicantInformation:EmailAddress",
        "InputObjectQuerySequence": 0,
        "IsDisabled": false,
        "IsLocked": false,
        "IsRequiredForUpsert": false,
        "IsUpsertKey": false,
        "LinkedObjectSequence": 0,
        "MayEdit": true,
        "Name": "LPIPopulateDCMPD219",
        "OmniDataTransformationId": {
            "Name": "LPIPopulateDCMPD219",
            "VlocityDataPackType": "VlocityMatchingKeyObject",
            "VlocityMatchingRecordSourceKey": "OmniDataTransform/LPIPopulateDCMPD219",
            "VlocityRecordSObjectType": "OmniDataTransform"
        },
        "OutputCreationSequence": 1,
        "OutputFieldName": "PurchaserEmail",
        "OutputObjectName": "json",
        "VlocityDataPackType": "SObject",
        "VlocityRecordSObjectType": "OmniDataTransformItem"
    },
    {
        "CurrencyIsoCode": "USD",
        "FilterGroup": 0,
        "GlobalKey": "LPIPopulateDCMPD21909994765634125113",
        "InputFieldName": "PurchaserFullName",
        "InputObjectQuerySequence": 0,
        "IsDisabled": false,
        "IsLocked": false,
        "IsRequiredForUpsert": false,
        "IsUpsertKey": false,
        "LinkedObjectSequence": 0,
        "MayEdit": true,
        "Name": "LPIPopulateDCMPD219",
        "OmniDataTransformationId": {
            "Name": "LPIPopulateDCMPD219",
            "VlocityDataPackType": "VlocityMatchingKeyObject",
            "VlocityMatchingRecordSourceKey": "OmniDataTransform/LPIPopulateDCMPD219",
            "VlocityRecordSObjectType": "OmniDataTransform"
        },
        "OutputCreationSequence": 1,
        "OutputFieldName": "PurchaserName",
        "OutputObjectName": "json",
        "VlocityDataPackType": "SObject",
        "VlocityRecordSObjectType": "OmniDataTransformItem"
    },
    {
        "CurrencyIsoCode": "USD",
        "FilterGroup": 0,
        "GlobalKey": "LPIPopulateDCMPD2196973402337308319",
        "InputFieldName": "ApplicantInformation:OccupationNameOfBusiness",
        "InputObjectQuerySequence": 0,
        "IsDisabled": false,
        "IsLocked": false,
        "IsRequiredForUpsert": false,
        "IsUpsertKey": false,
        "LinkedObjectSequence": 0,
        "MayEdit": true,
        "Name": "LPIPopulateDCMPD219",
        "OmniDataTransformationId": {
            "Name": "LPIPopulateDCMPD219",
            "VlocityDataPackType": "VlocityMatchingKeyObject",
            "VlocityMatchingRecordSourceKey": "OmniDataTransform/LPIPopulateDCMPD219",
            "VlocityRecordSObjectType": "OmniDataTransform"
        },
        "OutputCreationSequence": 1,
        "OutputFieldName": "PurchaserOccupation",
        "OutputObjectName": "json",
        "VlocityDataPackType": "SObject",
        "VlocityRecordSObjectType": "OmniDataTransformItem"
    },
    {
        "CurrencyIsoCode": "USD",
        "FilterGroup": 0,
        "GlobalKey": "LPIPopulateDCMPD2192455174855033031",
        "InputFieldName": "ApplicantInformation:PlaceOfBirth",
        "InputObjectQuerySequence": 0,
        "IsDisabled": false,
        "IsLocked": false,
        "IsRequiredForUpsert": false,
        "IsUpsertKey": false,
        "LinkedObjectSequence": 0,
        "MayEdit": true,
        "Name": "LPIPopulateDCMPD219",
        "OmniDataTransformationId": {
            "Name": "LPIPopulateDCMPD219",
            "VlocityDataPackType": "VlocityMatchingKeyObject",
            "VlocityMatchingRecordSourceKey": "OmniDataTransform/LPIPopulateDCMPD219",
            "VlocityRecordSObjectType": "OmniDataTransform"
        },
        "OutputCreationSequence": 1,
        "OutputFieldName": "PurchaserPlaceOfBirth",
        "OutputObjectName": "json",
        "VlocityDataPackType": "SObject",
        "VlocityRecordSObjectType": "OmniDataTransformItem"
    },
    {
        "CurrencyIsoCode": "USD",
        "FilterGroup": 0,
        "GlobalKey": "LPIPopulateDCMPD2194890769213636079",
        "InputFieldName": "ApplicantInformation:Race",
        "InputObjectQuerySequence": 0,
        "IsDisabled": false,
        "IsLocked": false,
        "IsRequiredForUpsert": false,
        "IsUpsertKey": false,
        "LinkedObjectSequence": 0,
        "MayEdit": true,
        "Name": "LPIPopulateDCMPD219",
        "OmniDataTransformationId": {
            "Name": "LPIPopulateDCMPD219",
            "VlocityDataPackType": "VlocityMatchingKeyObject",
            "VlocityMatchingRecordSourceKey": "OmniDataTransform/LPIPopulateDCMPD219",
            "VlocityRecordSObjectType": "OmniDataTransform"
        },
        "OutputCreationSequence": 1,
        "OutputFieldName": "PurchaserRace",
        "OutputObjectName": "json",
        "VlocityDataPackType": "SObject",
        "VlocityRecordSObjectType": "OmniDataTransformItem"
    },
    {
        "CurrencyIsoCode": "USD",
        "FilterGroup": 0,
        "GlobalKey": "LPIPopulateDCMPD2194388259930199969",
        "InputFieldName": "ApplicantInformation:Sex",
        "InputObjectQuerySequence": 0,
        "IsDisabled": false,
        "IsLocked": false,
        "IsRequiredForUpsert": false,
        "IsUpsertKey": false,
        "LinkedObjectSequence": 0,
        "MayEdit": true,
        "Name": "LPIPopulateDCMPD219",
        "OmniDataTransformationId": {
            "Name": "LPIPopulateDCMPD219",
            "VlocityDataPackType": "VlocityMatchingKeyObject",
            "VlocityMatchingRecordSourceKey": "OmniDataTransform/LPIPopulateDCMPD219",
            "VlocityRecordSObjectType": "OmniDataTransform"
        },
        "OutputCreationSequence": 1,
        "OutputFieldName": "PurchaserSex",
        "OutputObjectName": "json",
        "VlocityDataPackType": "SObject",
        "VlocityRecordSObjectType": "OmniDataTransformItem"
    },
    {
        "CurrencyIsoCode": "USD",
        "FilterGroup": 0,
        "GlobalKey": "LPIPopulateDCMPD2193600771977157604",
        "InputFieldName": "PDFStreet",
        "InputObjectQuerySequence": 0,
        "IsDisabled": false,
        "IsLocked": false,
        "IsRequiredForUpsert": false,
        "IsUpsertKey": false,
        "LinkedObjectSequence": 0,
        "MayEdit": true,
        "Name": "LPIPopulateDCMPD219",
        "OmniDataTransformationId": {
            "Name": "LPIPopulateDCMPD219",
            "VlocityDataPackType": "VlocityMatchingKeyObject",
            "VlocityMatchingRecordSourceKey": "OmniDataTransform/LPIPopulateDCMPD219",
            "VlocityRecordSObjectType": "OmniDataTransform"
        },
        "OutputCreationSequence": 1,
        "OutputFieldName": "PurchaserStreet",
        "OutputObjectName": "json",
        "VlocityDataPackType": "SObject",
        "VlocityRecordSObjectType": "OmniDataTransformItem"
    },
    {
        "CurrencyIsoCode": "USD",
        "FilterGroup": 0,
        "GlobalKey": "LPIPopulateDCMPD2192239984096114458",
        "InputFieldName": "PDFPostalCode",
        "InputObjectQuerySequence": 0,
        "IsDisabled": false,
        "IsLocked": false,
        "IsRequiredForUpsert": false,
        "IsUpsertKey": false,
        "LinkedObjectSequence": 0,
        "MayEdit": true,
        "Name": "LPIPopulateDCMPD219",
        "OmniDataTransformationId": {
            "Name": "LPIPopulateDCMPD219",
            "VlocityDataPackType": "VlocityMatchingKeyObject",
            "VlocityMatchingRecordSourceKey": "OmniDataTransform/LPIPopulateDCMPD219",
            "VlocityRecordSObjectType": "OmniDataTransform"
        },
        "OutputCreationSequence": 1,
        "OutputFieldName": "PurchaserZip",
        "OutputObjectName": "json",
        "VlocityDataPackType": "SObject",
        "VlocityRecordSObjectType": "OmniDataTransformItem"
    },
    {
        "CurrencyIsoCode": "USD",
        "FilterGroup": 0,
        "GlobalKey": "LPIPopulateDCMPD2195079656419462353",
        "InputFieldName": "PDFCity",
        "InputObjectQuerySequence": 0,
        "IsDisabled": false,
        "IsLocked": false,
        "IsRequiredForUpsert": false,
        "IsUpsertKey": false,
        "LinkedObjectSequence": 0,
        "MayEdit": true,
        "Name": "LPIPopulateDCMPD219",
        "OmniDataTransformationId": {
            "Name": "LPIPopulateDCMPD219",
            "VlocityDataPackType": "VlocityMatchingKeyObject",
            "VlocityMatchingRecordSourceKey": "OmniDataTransform/LPIPopulateDCMPD219",
            "VlocityRecordSObjectType": "OmniDataTransform"
        },
        "OutputCreationSequence": 1,
        "OutputFieldName": "PurchasherCity",
        "OutputObjectName": "json",
        "VlocityDataPackType": "SObject",
        "VlocityRecordSObjectType": "OmniDataTransformItem"
    },
    {
        "CurrencyIsoCode": "USD",
        "FilterGroup": 0,
        "GlobalKey": "LPIPopulateDCMPD21946047347316165754",
        "InputFieldName": "FirearmsRegistration:SellerCity",
        "InputObjectQuerySequence": 0,
        "IsDisabled": false,
        "IsLocked": false,
        "IsRequiredForUpsert": false,
        "IsUpsertKey": false,
        "LinkedObjectSequence": 0,
        "MayEdit": true,
        "Name": "LPIPopulateDCMPD219",
        "OmniDataTransformationId": {
            "Name": "LPIPopulateDCMPD219",
            "VlocityDataPackType": "VlocityMatchingKeyObject",
            "VlocityMatchingRecordSourceKey": "OmniDataTransform/LPIPopulateDCMPD219",
            "VlocityRecordSObjectType": "OmniDataTransform"
        },
        "OutputCreationSequence": 1,
        "OutputFieldName": "SellerCity",
        "OutputObjectName": "json",
        "VlocityDataPackType": "SObject",
        "VlocityRecordSObjectType": "OmniDataTransformItem"
    },
    {
        "CurrencyIsoCode": "USD",
        "FilterGroup": 0,
        "GlobalKey": "LPIPopulateDCMPD21943395553808989074",
        "InputFieldName": "FirearmsRegistration:SellerName",
        "InputObjectQuerySequence": 0,
        "IsDisabled": false,
        "IsLocked": false,
        "IsRequiredForUpsert": false,
        "IsUpsertKey": false,
        "LinkedObjectSequence": 0,
        "MayEdit": true,
        "Name": "LPIPopulateDCMPD219",
        "OmniDataTransformationId": {
            "Name": "LPIPopulateDCMPD219",
            "VlocityDataPackType": "VlocityMatchingKeyObject",
            "VlocityMatchingRecordSourceKey": "OmniDataTransform/LPIPopulateDCMPD219",
            "VlocityRecordSObjectType": "OmniDataTransform"
        },
        "OutputCreationSequence": 1,
        "OutputFieldName": "SellerName",
        "OutputObjectName": "json",
        "VlocityDataPackType": "SObject",
        "VlocityRecordSObjectType": "OmniDataTransformItem"
    },
    {
        "CurrencyIsoCode": "USD",
        "FilterGroup": 0,
        "GlobalKey": "LPIPopulateDCMPD2198782740994702132",
        "InputFieldName": "FirearmsRegistration:SellerStreetAddress",
        "InputObjectQuerySequence": 0,
        "IsDisabled": false,
        "IsLocked": false,
        "IsRequiredForUpsert": false,
        "IsUpsertKey": false,
        "LinkedObjectSequence": 0,
        "MayEdit": true,
        "Name": "LPIPopulateDCMPD219",
        "OmniDataTransformationId": {
            "Name": "LPIPopulateDCMPD219",
            "VlocityDataPackType": "VlocityMatchingKeyObject",
            "VlocityMatchingRecordSourceKey": "OmniDataTransform/LPIPopulateDCMPD219",
            "VlocityRecordSObjectType": "OmniDataTransform"
        },
        "OutputCreationSequence": 1,
        "OutputFieldName": "SellerStreet",
        "OutputObjectName": "json",
        "VlocityDataPackType": "SObject",
        "VlocityRecordSObjectType": "OmniDataTransformItem"
    },
    {
        "CurrencyIsoCode": "USD",
        "FilterGroup": 0,
        "GlobalKey": "LPIPopulateDCMPD2197067897489470181",
        "InputFieldName": "FirearmsRegistration:SellerZipCode",
        "InputObjectQuerySequence": 0,
        "IsDisabled": false,
        "IsLocked": false,
        "IsRequiredForUpsert": false,
        "IsUpsertKey": false,
        "LinkedObjectSequence": 0,
        "MayEdit": true,
        "Name": "LPIPopulateDCMPD219",
        "OmniDataTransformationId": {
            "Name": "LPIPopulateDCMPD219",
            "VlocityDataPackType": "VlocityMatchingKeyObject",
            "VlocityMatchingRecordSourceKey": "OmniDataTransform/LPIPopulateDCMPD219",
            "VlocityRecordSObjectType": "OmniDataTransform"
        },
        "OutputCreationSequence": 1,
        "OutputFieldName": "SellerZip",
        "OutputObjectName": "json",
        "VlocityDataPackType": "SObject",
        "VlocityRecordSObjectType": "OmniDataTransformItem"
    },
    {
        "CurrencyIsoCode": "USD",
        "FilterGroup": 0,
        "GlobalKey": "LPIPopulateDCMPD21906732995840940803",
        "InputFieldName": "FormulaSerialNumber",
        "InputObjectQuerySequence": 0,
        "IsDisabled": false,
        "IsLocked": false,
        "IsRequiredForUpsert": false,
        "IsUpsertKey": false,
        "LinkedObjectSequence": 0,
        "MayEdit": true,
        "Name": "LPIPopulateDCMPD219",
        "OmniDataTransformationId": {
            "Name": "LPIPopulateDCMPD219",
            "VlocityDataPackType": "VlocityMatchingKeyObject",
            "VlocityMatchingRecordSourceKey": "OmniDataTransform/LPIPopulateDCMPD219",
            "VlocityRecordSObjectType": "OmniDataTransform"
        },
        "OutputCreationSequence": 1,
        "OutputFieldName": "SerialNumber",
        "OutputObjectName": "json",
        "VlocityDataPackType": "SObject",
        "VlocityRecordSObjectType": "OmniDataTransformItem"
    },
    {
        "CurrencyIsoCode": "USD",
        "FilterGroup": 0,
        "GlobalKey": "LPIPopulateDCMPD2195836123161297231",
        "InputFieldName": "FirearmsRegistration:TypeOfAction",
        "InputObjectQuerySequence": 0,
        "IsDisabled": false,
        "IsLocked": false,
        "IsRequiredForUpsert": false,
        "IsUpsertKey": false,
        "LinkedObjectSequence": 0,
        "MayEdit": true,
        "Name": "LPIPopulateDCMPD219",
        "OmniDataTransformationId": {
            "Name": "LPIPopulateDCMPD219",
            "VlocityDataPackType": "VlocityMatchingKeyObject",
            "VlocityMatchingRecordSourceKey": "OmniDataTransform/LPIPopulateDCMPD219",
            "VlocityRecordSObjectType": "OmniDataTransform"
        },
        "OutputCreationSequence": 1,
        "OutputFieldName": "TypeOfAction",
        "OutputObjectName": "json",
        "VlocityDataPackType": "SObject",
        "VlocityRecordSObjectType": "OmniDataTransformItem"
    },
    {
        "CurrencyIsoCode": "USD",
        "FilterGroup": 0,
        "GlobalKey": "LPIPopulateDCMPD2195549043788231482",
        "InputFieldName": "PastAddress1",
        "InputObjectQuerySequence": 0,
        "IsDisabled": false,
        "IsLocked": false,
        "IsRequiredForUpsert": false,
        "IsUpsertKey": false,
        "LinkedObjectSequence": 0,
        "MayEdit": true,
        "Name": "LPIPopulateDCMPD219",
        "OmniDataTransformationId": {
            "Name": "LPIPopulateDCMPD219",
            "VlocityDataPackType": "VlocityMatchingKeyObject",
            "VlocityMatchingRecordSourceKey": "OmniDataTransform/LPIPopulateDCMPD219",
            "VlocityRecordSObjectType": "OmniDataTransform"
        },
        "OutputCreationSequence": 1,
        "OutputFieldName": "past address 1",
        "OutputObjectName": "json",
        "VlocityDataPackType": "SObject",
        "VlocityRecordSObjectType": "OmniDataTransformItem"
    }
]