{
    "CurrencyIsoCode": "USD",
    "IsActive": true,
    "IsLocked": false,
    "IsOmniScriptEmbeddable": false,
    "MayEdit": true,
    "Name": "SetContextData",
    "OmniProcessId": {
        "Name": "Caseworker Guided Flow",
        "VlocityDataPackType": "VlocityMatchingKeyObject",
        "VlocityMatchingRecordSourceKey": "OmniProcess/BenefitManagement/CaseworkerGuidedFlow/English",
        "VlocityRecordSObjectType": "OmniProcess"
    },
    "PropertySetConfig": {
        "HTMLTemplateId": "",
        "controlWidth": 12,
        "elementValueMap": {
            "ContextData": {
                "id": "%ContextId%",
                "redirectUrl": "%IAData:redirectUrl%"
            }
        },
        "label": "SetContextData",
        "message": {
        },
        "pubsub": false,
        "show": null,
        "showPersistentComponent": [
            true,
            false
        ],
        "ssm": false,
        "wpm": false
    },
    "Type": "Set Values",
    "VlocityDataPackType": "SObject",
    "VlocityRecordSObjectType": "OmniProcessElement",
    "VlocityRecordSourceKey": "OmniProcessElement/OmniProcess/BenefitManagement/CaseworkerGuidedFlow/English/SetContextData"
}