{
    "CurrencyIsoCode": "USD",
    "IsActive": true,
    "IsLocked": false,
    "IsOmniScriptEmbeddable": false,
    "MayEdit": true,
    "Name": "HousingType",
    "OmniProcessId": {
        "Name": "Community Development Grant",
        "VlocityDataPackType": "VlocityMatchingKeyObject",
        "VlocityMatchingRecordSourceKey": "OmniProcess/Grants/BlockMatchingGrant/English",
        "VlocityRecordSObjectType": "OmniProcess"
    },
    "ParentElementId": {
        "Name": "ProjectNameInformationStep",
        "OmniProcessId": {
            "Name": "Community Development Grant",
            "VlocityDataPackType": "VlocityMatchingKeyObject",
            "VlocityMatchingRecordSourceKey": "OmniProcess/Grants/BlockMatchingGrant/English",
            "VlocityRecordSObjectType": "OmniProcess"
        },
        "VlocityDataPackType": "VlocityMatchingKeyObject",
        "VlocityMatchingRecordSourceKey": "OmniProcessElement/OmniProcess/Grants/BlockMatchingGrant/English/ProjectNameInformationStep",
        "VlocityRecordSObjectType": "OmniProcessElement"
    },
    "ParentElementName": "ProjectNameInformationStep",
    "ParentElementType": "Step",
    "PropertySetConfig": {
        "HTMLTemplateId": "",
        "accessibleInFutureSteps": false,
        "conditionType": "Hide if False",
        "controlWidth": 4,
        "controllingField": {
            "element": "",
            "source": "",
            "type": ""
        },
        "defaultValue": null,
        "disOnTplt": false,
        "enableCaption": true,
        "help": false,
        "helpText": "",
        "hide": false,
        "horizontalMode": false,
        "imageCountInRow": 3,
        "label": "Housing Type:",
        "optionHeight": 100,
        "optionSource": {
            "source": "",
            "type": ""
        },
        "optionWidth": 100,
        "options": [
            {
                "autoAdv": null,
                "name": "Rental",
                "value": "Rental"
            },
            {
                "autoAdv": null,
                "name": "Homeownership",
                "value": "Homeownership"
            },
            {
                "autoAdv": null,
                "name": "Both",
                "value": "Both"
            },
            {
                "autoAdv": null,
                "name": "Neither",
                "value": "Neither"
            }
        ],
        "readOnly": false,
        "repeat": false,
        "repeatClone": false,
        "repeatLimit": null,
        "required": true,
        "show": null
    },
    "Type": "Select",
    "VlocityDataPackType": "SObject",
    "VlocityRecordSObjectType": "OmniProcessElement",
    "VlocityRecordSourceKey": "OmniProcessElement/OmniProcess/Grants/BlockMatchingGrant/English/HousingType"
}