{
    "CurrencyIsoCode": "USD",
    "IsActive": true,
    "IsLocked": false,
    "IsOmniScriptEmbeddable": false,
    "MayEdit": true,
    "Name": "EvaluateHouseholdActionType",
    "OmniProcessId": {
        "Name": "FetchApplicationSummaryInformation",
        "VlocityDataPackType": "VlocityMatchingKeyObject",
        "VlocityMatchingRecordSourceKey": "OmniProcess/BenefitManagement/FetchApplicationSummaryInformation/Procedure",
        "VlocityRecordSObjectType": "OmniProcess"
    },
    "ParentElementId": {
        "Name": "LoopHouseholdMemberDetails",
        "OmniProcessId": {
            "Name": "FetchApplicationSummaryInformation",
            "VlocityDataPackType": "VlocityMatchingKeyObject",
            "VlocityMatchingRecordSourceKey": "OmniProcess/BenefitManagement/FetchApplicationSummaryInformation/Procedure",
            "VlocityRecordSObjectType": "OmniProcess"
        },
        "VlocityDataPackType": "VlocityMatchingKeyObject",
        "VlocityMatchingRecordSourceKey": "OmniProcessElement/OmniProcess/BenefitManagement/FetchApplicationSummaryInformation/Procedure/LoopHouseholdMemberDetails",
        "VlocityRecordSObjectType": "OmniProcessElement"
    },
    "ParentElementName": "LoopHouseholdMemberDetails",
    "ParentElementType": "Loop Block",
    "PropertySetConfig": {
        "actionMessage": "",
        "chainOnStep": false,
        "disOnTplt": false,
        "elementValueMap": {
            "ishouseholdactiontype": true
        },
        "executionConditionalFormula": "(TransformedAQR:GenericData:HouseholdMemberDetails:ActionType == \"Update\") || (TransformedAQR:GenericData:HouseholdMemberDetails:ActionType == \"Remove\") || (TransformedAQR:GenericData:HouseholdMemberDetails:ActionType == \"Add\")",
        "failOnStepError": true,
        "failureConditionalFormula": "",
        "label": "SetValues18",
        "responseJSONNode": "Arehouseholdactiontype",
        "responseJSONPath": "ishouseholdactiontype",
        "show": null
    },
    "Type": "Set Values",
    "VlocityDataPackType": "SObject",
    "VlocityRecordSObjectType": "OmniProcessElement",
    "VlocityRecordSourceKey": "OmniProcessElement/OmniProcess/BenefitManagement/FetchApplicationSummaryInformation/Procedure/EvaluateHouseholdActionType"
}