{
    "CurrencyIsoCode": "USD",
    "IsActive": true,
    "IsLocked": false,
    "IsOmniScriptEmbeddable": false,
    "MayEdit": true,
    "Name": "SetValuesCertificateOfCapacity",
    "OmniProcessId": {
        "Name": "File A Claim",
        "VlocityDataPackType": "VlocityMatchingKeyObject",
        "VlocityMatchingRecordSourceKey": "OmniProcess/SocialInsurance/FileClaim/English",
        "VlocityRecordSObjectType": "OmniProcess"
    },
    "ParentElementId": {
        "Name": "CertificateOfCapacity",
        "OmniProcessId": {
            "Name": "File A Claim",
            "VlocityDataPackType": "VlocityMatchingKeyObject",
            "VlocityMatchingRecordSourceKey": "OmniProcess/SocialInsurance/FileClaim/English",
            "VlocityRecordSObjectType": "OmniProcess"
        },
        "VlocityDataPackType": "VlocityMatchingKeyObject",
        "VlocityMatchingRecordSourceKey": "OmniProcessElement/OmniProcess/SocialInsurance/FileClaim/English/CertificateOfCapacity",
        "VlocityRecordSObjectType": "OmniProcessElement"
    },
    "ParentElementName": "CertificateOfCapacity",
    "ParentElementType": "Step",
    "PropertySetConfig": {
        "HTMLTemplateId": "",
        "controlWidth": 1,
        "elementValueMap": {
            "HealthcareProviderTypeAhead-Block": {
                "HealthcareProviderTypeAhead": "%HealthcareProvider:Name%",
                "PSS_SI_v1_HealthcareProviderId": "%HealthcareProvider:Id%",
                "PSS_SI_v1_ProviderName": "%HealthcareProvider:Name%"
            },
            "PSS_SI_v1_FromDate": "=NOW()",
            "PSS_SI_v1_InjuryType": "Fracture",
            "PSS_SI_v1_IssuedDate": "=MOMENT(NOW()).subtract(1,'day')",
            "PSS_SI_v1_ProviderContactNumber": "8008675309",
            "PSS_SI_v1_ToDate": "=MOMENT(NOW()).add(42,'day')",
            "PSS_SI_v1_UploadDocument": null,
            "PSS_SI_v1_WorkerCapacity": 25
        },
        "label": ">>",
        "message": {
        },
        "pubsub": false,
        "show": null,
        "showPersistentComponent": [
            true,
            false
        ],
        "ssm": false,
        "wpm": false
    },
    "Type": "Set Values",
    "VlocityDataPackType": "SObject",
    "VlocityRecordSObjectType": "OmniProcessElement",
    "VlocityRecordSourceKey": "OmniProcessElement/OmniProcess/SocialInsurance/FileClaim/English/SetValuesCertificateOfCapacity"
}