{
    "CurrencyIsoCode": "USD",
    "IsActive": true,
    "IsLocked": false,
    "IsOmniScriptEmbeddable": false,
    "MayEdit": true,
    "Name": "TextBlock11",
    "OmniProcessId": {
        "Name": "Psychiatric Residential Treatment Facility",
        "VlocityDataPackType": "VlocityMatchingKeyObject",
        "VlocityMatchingRecordSourceKey": "OmniProcess/LicensingAndPermitting/PsychiatricResidentialTreatmentFacility/English",
        "VlocityRecordSObjectType": "OmniProcess"
    },
    "ParentElementId": {
        "Name": "PhysicalPlant",
        "OmniProcessId": {
            "Name": "Psychiatric Residential Treatment Facility",
            "VlocityDataPackType": "VlocityMatchingKeyObject",
            "VlocityMatchingRecordSourceKey": "OmniProcess/LicensingAndPermitting/PsychiatricResidentialTreatmentFacility/English",
            "VlocityRecordSObjectType": "OmniProcess"
        },
        "VlocityDataPackType": "VlocityMatchingKeyObject",
        "VlocityMatchingRecordSourceKey": "OmniProcessElement/OmniProcess/LicensingAndPermitting/PsychiatricResidentialTreatmentFacility/English/PhysicalPlant",
        "VlocityRecordSObjectType": "OmniProcessElement"
    },
    "ParentElementName": "PhysicalPlant",
    "ParentElementType": "Step",
    "PropertySetConfig": {
        "HTMLTemplateId": "",
        "controlWidth": 12,
        "dataJSON": false,
        "label": "TextBlock11",
        "sanitize": false,
        "show": null,
        "text": "<p class=\"p1\"><strong>Provide a plot plan of the entire outdoor premises and a floor plan of each building with linear measurements of rooms. Label&nbsp;each room as to purpose. Indicate placement of all closets and cabinets, each toilet, sink, bathtub and/or shower. Indicate&nbsp;placement and linear measurements of door and window openings.&nbsp; Please attach in the Documentation Information section in a later section of the application.</strong></p>",
        "textKey": ""
    },
    "Type": "Text Block",
    "VlocityDataPackType": "SObject",
    "VlocityRecordSObjectType": "OmniProcessElement",
    "VlocityRecordSourceKey": "OmniProcessElement/OmniProcess/LicensingAndPermitting/PsychiatricResidentialTreatmentFacility/English/TextBlock11"
}