[
    {
        "CurrencyIsoCode": "USD",
        "GlobalKey": "GPSTalentManagementUpsertAFRCustom114",
        "InputFieldName": "ApplicationFormId",
        "IsDisabled": false,
        "IsLocked": false,
        "IsRequiredForUpsert": false,
        "IsUpsertKey": true,
        "MayEdit": true,
        "Name": "GPSTalentManagementUpsertAFR",
        "OmniDataTransformationId": {
            "Name": "GPSTalentManagementUpsertAFR",
            "VlocityDataPackType": "VlocityMatchingKeyObject",
            "VlocityMatchingRecordSourceKey": "OmniDataTransform/GPSTalentManagementUpsertAFR",
            "VlocityRecordSObjectType": "OmniDataTransform"
        },
        "OutputCreationSequence": 1,
        "OutputFieldName": "ApplicationFormId",
        "OutputObjectName": "ApplicationFormRelation",
        "VlocityDataPackType": "SObject",
        "VlocityRecordSObjectType": "OmniDataTransformItem"
    },
    {
        "CurrencyIsoCode": "USD",
        "FilterOperator": "=",
        "GlobalKey": "GPSTalentManagementUpsertAFRCustom7268",
        "IsDisabled": true,
        "IsLocked": false,
        "IsRequiredForUpsert": false,
        "IsUpsertKey": false,
        "MayEdit": true,
        "MigrationValue": "FAKEMAPPING",
        "Name": "GPSTalentManagementUpsertAFR",
        "OmniDataTransformationId": {
            "Name": "GPSTalentManagementUpsertAFR",
            "VlocityDataPackType": "VlocityMatchingKeyObject",
            "VlocityMatchingRecordSourceKey": "OmniDataTransform/GPSTalentManagementUpsertAFR",
            "VlocityRecordSObjectType": "OmniDataTransform"
        },
        "OutputCreationSequence": 1,
        "OutputFieldName": "Id",
        "OutputObjectName": "ApplicationFormRelation",
        "VlocityDataPackType": "SObject",
        "VlocityRecordSObjectType": "OmniDataTransformItem"
    },
    {
        "CurrencyIsoCode": "USD",
        "GlobalKey": "GPSTalentManagementUpsertAFRCustom5899",
        "InputFieldName": "RequisitionId",
        "IsDisabled": false,
        "IsLocked": false,
        "IsRequiredForUpsert": false,
        "IsUpsertKey": true,
        "MayEdit": true,
        "Name": "GPSTalentManagementUpsertAFR",
        "OmniDataTransformationId": {
            "Name": "GPSTalentManagementUpsertAFR",
            "VlocityDataPackType": "VlocityMatchingKeyObject",
            "VlocityMatchingRecordSourceKey": "OmniDataTransform/GPSTalentManagementUpsertAFR",
            "VlocityRecordSObjectType": "OmniDataTransform"
        },
        "OutputCreationSequence": 1,
        "OutputFieldName": "ReferenceRecordId",
        "OutputObjectName": "ApplicationFormRelation",
        "VlocityDataPackType": "SObject",
        "VlocityRecordSObjectType": "OmniDataTransformItem"
    },
    {
        "CurrencyIsoCode": "USD",
        "GlobalKey": "GPSTalentManagementUpsertAFRCustom6468",
        "InputFieldName": "EducationScoreExplanation",
        "IsDisabled": false,
        "IsLocked": false,
        "IsRequiredForUpsert": false,
        "IsUpsertKey": false,
        "MayEdit": true,
        "Name": "GPSTalentManagementUpsertAFR",
        "OmniDataTransformationId": {
            "Name": "GPSTalentManagementUpsertAFR",
            "VlocityDataPackType": "VlocityMatchingKeyObject",
            "VlocityMatchingRecordSourceKey": "OmniDataTransform/GPSTalentManagementUpsertAFR",
            "VlocityRecordSObjectType": "OmniDataTransform"
        },
        "OutputCreationSequence": 1,
        "OutputFieldName": "gps_Education_Score_Explanation__c",
        "OutputObjectName": "ApplicationFormRelation",
        "VlocityDataPackType": "SObject",
        "VlocityRecordSObjectType": "OmniDataTransformItem"
    },
    {
        "CurrencyIsoCode": "USD",
        "GlobalKey": "GPSTalentManagementUpsertAFRCustom7479",
        "InputFieldName": "EducationScore",
        "IsDisabled": false,
        "IsLocked": false,
        "IsRequiredForUpsert": false,
        "IsUpsertKey": false,
        "MayEdit": true,
        "Name": "GPSTalentManagementUpsertAFR",
        "OmniDataTransformationId": {
            "Name": "GPSTalentManagementUpsertAFR",
            "VlocityDataPackType": "VlocityMatchingKeyObject",
            "VlocityMatchingRecordSourceKey": "OmniDataTransform/GPSTalentManagementUpsertAFR",
            "VlocityRecordSObjectType": "OmniDataTransform"
        },
        "OutputCreationSequence": 1,
        "OutputFieldName": "gps_Education_Score__c",
        "OutputObjectName": "ApplicationFormRelation",
        "VlocityDataPackType": "SObject",
        "VlocityRecordSObjectType": "OmniDataTransformItem"
    },
    {
        "CurrencyIsoCode": "USD",
        "GlobalKey": "GPSTalentManagementUpsertAFRCustom3390",
        "InputFieldName": "ExperienceExplanation",
        "IsDisabled": false,
        "IsLocked": false,
        "IsRequiredForUpsert": false,
        "IsUpsertKey": false,
        "MayEdit": true,
        "Name": "GPSTalentManagementUpsertAFR",
        "OmniDataTransformationId": {
            "Name": "GPSTalentManagementUpsertAFR",
            "VlocityDataPackType": "VlocityMatchingKeyObject",
            "VlocityMatchingRecordSourceKey": "OmniDataTransform/GPSTalentManagementUpsertAFR",
            "VlocityRecordSObjectType": "OmniDataTransform"
        },
        "OutputCreationSequence": 1,
        "OutputFieldName": "gps_Experience_Score_Explanation__c",
        "OutputObjectName": "ApplicationFormRelation",
        "VlocityDataPackType": "SObject",
        "VlocityRecordSObjectType": "OmniDataTransformItem"
    },
    {
        "CurrencyIsoCode": "USD",
        "GlobalKey": "GPSTalentManagementUpsertAFRCustom9352",
        "InputFieldName": "ExperienceScore",
        "IsDisabled": false,
        "IsLocked": false,
        "IsRequiredForUpsert": false,
        "IsUpsertKey": false,
        "MayEdit": true,
        "Name": "GPSTalentManagementUpsertAFR",
        "OmniDataTransformationId": {
            "Name": "GPSTalentManagementUpsertAFR",
            "VlocityDataPackType": "VlocityMatchingKeyObject",
            "VlocityMatchingRecordSourceKey": "OmniDataTransform/GPSTalentManagementUpsertAFR",
            "VlocityRecordSObjectType": "OmniDataTransform"
        },
        "OutputCreationSequence": 1,
        "OutputFieldName": "gps_Experience_Score__c",
        "OutputObjectName": "ApplicationFormRelation",
        "VlocityDataPackType": "SObject",
        "VlocityRecordSObjectType": "OmniDataTransformItem"
    },
    {
        "CurrencyIsoCode": "USD",
        "GlobalKey": "GPSTalentManagementUpsertAFRCustom5148",
        "InputFieldName": "ValidLocationExplanation",
        "IsDisabled": false,
        "IsLocked": false,
        "IsRequiredForUpsert": false,
        "IsUpsertKey": false,
        "MayEdit": true,
        "Name": "GPSTalentManagementUpsertAFR",
        "OmniDataTransformationId": {
            "Name": "GPSTalentManagementUpsertAFR",
            "VlocityDataPackType": "VlocityMatchingKeyObject",
            "VlocityMatchingRecordSourceKey": "OmniDataTransform/GPSTalentManagementUpsertAFR",
            "VlocityRecordSObjectType": "OmniDataTransform"
        },
        "OutputCreationSequence": 1,
        "OutputFieldName": "gps_Location_Explanation__c",
        "OutputObjectName": "ApplicationFormRelation",
        "VlocityDataPackType": "SObject",
        "VlocityRecordSObjectType": "OmniDataTransformItem"
    },
    {
        "CurrencyIsoCode": "USD",
        "GlobalKey": "GPSTalentManagementUpsertAFRCustom3476",
        "InputFieldName": "SkillsScoreExplanation",
        "IsDisabled": false,
        "IsLocked": false,
        "IsRequiredForUpsert": false,
        "IsUpsertKey": false,
        "MayEdit": true,
        "Name": "GPSTalentManagementUpsertAFR",
        "OmniDataTransformationId": {
            "Name": "GPSTalentManagementUpsertAFR",
            "VlocityDataPackType": "VlocityMatchingKeyObject",
            "VlocityMatchingRecordSourceKey": "OmniDataTransform/GPSTalentManagementUpsertAFR",
            "VlocityRecordSObjectType": "OmniDataTransform"
        },
        "OutputCreationSequence": 1,
        "OutputFieldName": "gps_Skills_Score_Explanation__c",
        "OutputObjectName": "ApplicationFormRelation",
        "VlocityDataPackType": "SObject",
        "VlocityRecordSObjectType": "OmniDataTransformItem"
    },
    {
        "CurrencyIsoCode": "USD",
        "GlobalKey": "GPSTalentManagementUpsertAFRCustom4262",
        "InputFieldName": "SkillsScore",
        "IsDisabled": false,
        "IsLocked": false,
        "IsRequiredForUpsert": false,
        "IsUpsertKey": false,
        "MayEdit": true,
        "Name": "GPSTalentManagementUpsertAFR",
        "OmniDataTransformationId": {
            "Name": "GPSTalentManagementUpsertAFR",
            "VlocityDataPackType": "VlocityMatchingKeyObject",
            "VlocityMatchingRecordSourceKey": "OmniDataTransform/GPSTalentManagementUpsertAFR",
            "VlocityRecordSObjectType": "OmniDataTransform"
        },
        "OutputCreationSequence": 1,
        "OutputFieldName": "gps_Skills_Score__c",
        "OutputObjectName": "ApplicationFormRelation",
        "VlocityDataPackType": "SObject",
        "VlocityRecordSObjectType": "OmniDataTransformItem"
    },
    {
        "CurrencyIsoCode": "USD",
        "GlobalKey": "GPSTalentManagementUpsertAFRCustom7821",
        "InputFieldName": "ValidLocation",
        "IsDisabled": false,
        "IsLocked": false,
        "IsRequiredForUpsert": false,
        "IsUpsertKey": false,
        "MayEdit": true,
        "Name": "GPSTalentManagementUpsertAFR",
        "OmniDataTransformationId": {
            "Name": "GPSTalentManagementUpsertAFR",
            "VlocityDataPackType": "VlocityMatchingKeyObject",
            "VlocityMatchingRecordSourceKey": "OmniDataTransform/GPSTalentManagementUpsertAFR",
            "VlocityRecordSObjectType": "OmniDataTransform"
        },
        "OutputCreationSequence": 1,
        "OutputFieldName": "gps_Valid_Location__c",
        "OutputObjectName": "ApplicationFormRelation",
        "TransformValueMappings": "{\"Yes\":\"true\",\"No\":\"false\"}",
        "VlocityDataPackType": "SObject",
        "VlocityRecordSObjectType": "OmniDataTransformItem"
    }
]