{
    "CurrencyIsoCode": "USD",
    "DiscoveryFrameworkUsageType": "Default",
    "IsActive": true,
    "IsLocked": false,
    "IsOmniScriptEmbeddable": false,
    "MayEdit": true,
    "Name": "Partner1_LastName",
    "OmniProcessId": {
        "Name": "Business License Application Salon",
        "VlocityDataPackType": "VlocityMatchingKeyObject",
        "VlocityMatchingRecordSourceKey": "OmniProcess/LicensingAndPermitting/BusinessSalon/English",
        "VlocityRecordSObjectType": "OmniProcess"
    },
    "ParentElementId": {
        "Name": "PartnershipOwnership",
        "OmniProcessId": {
            "Name": "Business License Application Salon",
            "VlocityDataPackType": "VlocityMatchingKeyObject",
            "VlocityMatchingRecordSourceKey": "OmniProcess/LicensingAndPermitting/BusinessSalon/English",
            "VlocityRecordSObjectType": "OmniProcess"
        },
        "VlocityDataPackType": "VlocityMatchingKeyObject",
        "VlocityMatchingRecordSourceKey": "OmniProcessElement/OmniProcess/LicensingAndPermitting/BusinessSalon/English/PartnershipOwnership",
        "VlocityRecordSObjectType": "OmniProcessElement"
    },
    "ParentElementName": "PartnershipOwnership",
    "ParentElementType": "Block",
    "PropertySetConfig": {
        "HTMLTemplateId": "",
        "accessibleInFutureSteps": false,
        "conditionType": "Hide if False",
        "controlWidth": 6,
        "debounceValue": 0,
        "defaultValue": null,
        "disOnTplt": false,
        "help": false,
        "helpText": "",
        "hide": false,
        "inputWidth": 12,
        "label": "Partner Last Name",
        "mask": "",
        "maxLength": 255,
        "minLength": 0,
        "pattern": "",
        "ptrnErrText": "",
        "readOnly": false,
        "repeat": false,
        "repeatClone": false,
        "repeatLimit": null,
        "required": false,
        "show": null,
        "showInputWidth": false
    },
    "Type": "Text",
    "VlocityDataPackType": "SObject",
    "VlocityRecordSObjectType": "OmniProcessElement",
    "VlocityRecordSourceKey": "OmniProcessElement/OmniProcess/LicensingAndPermitting/BusinessSalon/English/Partner1_LastName"
}