[
    {
        "CurrencyIsoCode": "USD",
        "FilterGroup": 0,
        "FilterOperator": "=",
        "FilterValue": "SampleUser",
        "GlobalKey": "ESRIGetAccountDetails1784407139136326",
        "InputFieldName": "Id",
        "InputObjectName": "User",
        "InputObjectQuerySequence": 1,
        "IsDisabled": false,
        "IsLocked": false,
        "IsRequiredForUpsert": false,
        "IsUpsertKey": false,
        "MayEdit": true,
        "Name": "ESRIGetAccountDetails",
        "OmniDataTransformationId": {
            "Name": "ESRIGetAccountDetails",
            "VlocityDataPackType": "VlocityMatchingKeyObject",
            "VlocityMatchingRecordSourceKey": "OmniDataTransform/ESRIGetAccountDetails",
            "VlocityRecordSObjectType": "OmniDataTransform"
        },
        "OutputCreationSequence": 0,
        "OutputFieldName": "User",
        "OutputObjectName": "json",
        "VlocityDataPackType": "SObject",
        "VlocityRecordSObjectType": "OmniDataTransformItem"
    },
    {
        "CurrencyIsoCode": "USD",
        "FilterGroup": 0,
        "FilterOperator": "=",
        "FilterValue": "User:ContactId",
        "GlobalKey": "ESRIGetAccountDetails7936839386536079",
        "InputFieldName": "Id",
        "InputObjectName": "Contact",
        "InputObjectQuerySequence": 2,
        "IsDisabled": false,
        "IsLocked": false,
        "IsRequiredForUpsert": false,
        "IsUpsertKey": false,
        "MayEdit": true,
        "Name": "ESRIGetAccountDetails",
        "OmniDataTransformationId": {
            "Name": "ESRIGetAccountDetails",
            "VlocityDataPackType": "VlocityMatchingKeyObject",
            "VlocityMatchingRecordSourceKey": "OmniDataTransform/ESRIGetAccountDetails",
            "VlocityRecordSObjectType": "OmniDataTransform"
        },
        "OutputCreationSequence": 0,
        "OutputFieldName": "Contact",
        "OutputObjectName": "json",
        "VlocityDataPackType": "SObject",
        "VlocityRecordSObjectType": "OmniDataTransformItem"
    },
    {
        "CurrencyIsoCode": "USD",
        "FilterGroup": 0,
        "FilterOperator": "=",
        "FilterValue": "Contact:AccountId",
        "GlobalKey": "ESRIGetAccountDetails9523224278539333",
        "InputFieldName": "Id",
        "InputObjectName": "Account",
        "InputObjectQuerySequence": 3,
        "IsDisabled": false,
        "IsLocked": false,
        "IsRequiredForUpsert": false,
        "IsUpsertKey": false,
        "MayEdit": true,
        "Name": "ESRIGetAccountDetails",
        "OmniDataTransformationId": {
            "Name": "ESRIGetAccountDetails",
            "VlocityDataPackType": "VlocityMatchingKeyObject",
            "VlocityMatchingRecordSourceKey": "OmniDataTransform/ESRIGetAccountDetails",
            "VlocityRecordSObjectType": "OmniDataTransform"
        },
        "OutputCreationSequence": 0,
        "OutputFieldName": "Account",
        "OutputObjectName": "json",
        "VlocityDataPackType": "SObject",
        "VlocityRecordSObjectType": "OmniDataTransformItem"
    },
    {
        "CurrencyIsoCode": "USD",
        "FormulaExpression": "CONCAT(Account:BillingStreet,\",\",Account:BillingCity,\",\",Account:BillingState,\",\",Account:BillingPostalCode)",
        "FormulaResultPath": "Address",
        "FormulaSequence": 1,
        "GlobalKey": "ESRIGetAccountDetails340174829595306",
        "IsDisabled": false,
        "IsLocked": false,
        "IsRequiredForUpsert": false,
        "IsUpsertKey": false,
        "MayEdit": true,
        "Name": "ESRIGetAccountDetails",
        "OmniDataTransformationId": {
            "Name": "ESRIGetAccountDetails",
            "VlocityDataPackType": "VlocityMatchingKeyObject",
            "VlocityMatchingRecordSourceKey": "OmniDataTransform/ESRIGetAccountDetails",
            "VlocityRecordSObjectType": "OmniDataTransform"
        },
        "OutputCreationSequence": 0,
        "OutputFieldName": "Formula",
        "OutputObjectName": "Formula",
        "VlocityDataPackType": "SObject",
        "VlocityRecordSObjectType": "OmniDataTransformItem"
    },
    {
        "CurrencyIsoCode": "USD",
        "GlobalKey": "ESRIGetAccountDetails5318219824467956",
        "InputFieldName": "Account:Id",
        "IsDisabled": false,
        "IsLocked": false,
        "IsRequiredForUpsert": false,
        "IsUpsertKey": false,
        "MayEdit": true,
        "Name": "ESRIGetAccountDetails",
        "OmniDataTransformationId": {
            "Name": "ESRIGetAccountDetails",
            "VlocityDataPackType": "VlocityMatchingKeyObject",
            "VlocityMatchingRecordSourceKey": "OmniDataTransform/ESRIGetAccountDetails",
            "VlocityRecordSObjectType": "OmniDataTransform"
        },
        "OutputCreationSequence": 1,
        "OutputFieldName": "AccountId",
        "OutputObjectName": "json",
        "VlocityDataPackType": "SObject",
        "VlocityRecordSObjectType": "OmniDataTransformItem"
    },
    {
        "CurrencyIsoCode": "USD",
        "GlobalKey": "ESRIGetAccountDetails9528282047984118",
        "InputFieldName": "Address",
        "IsDisabled": false,
        "IsLocked": false,
        "IsRequiredForUpsert": false,
        "IsUpsertKey": false,
        "MayEdit": true,
        "Name": "ESRIGetAccountDetails",
        "OmniDataTransformationId": {
            "Name": "ESRIGetAccountDetails",
            "VlocityDataPackType": "VlocityMatchingKeyObject",
            "VlocityMatchingRecordSourceKey": "OmniDataTransform/ESRIGetAccountDetails",
            "VlocityRecordSObjectType": "OmniDataTransform"
        },
        "OutputCreationSequence": 1,
        "OutputFieldName": "Address",
        "OutputObjectName": "json",
        "VlocityDataPackType": "SObject",
        "VlocityRecordSObjectType": "OmniDataTransformItem"
    },
    {
        "CurrencyIsoCode": "USD",
        "GlobalKey": "ESRIGetAccountDetails11454057464076683",
        "InputFieldName": "Account:Name",
        "IsDisabled": false,
        "IsLocked": false,
        "IsRequiredForUpsert": false,
        "IsUpsertKey": false,
        "MayEdit": true,
        "Name": "ESRIGetAccountDetails",
        "OmniDataTransformationId": {
            "Name": "ESRIGetAccountDetails",
            "VlocityDataPackType": "VlocityMatchingKeyObject",
            "VlocityMatchingRecordSourceKey": "OmniDataTransform/ESRIGetAccountDetails",
            "VlocityRecordSObjectType": "OmniDataTransform"
        },
        "OutputCreationSequence": 1,
        "OutputFieldName": "ApplicantInformation:AccountName",
        "OutputObjectName": "json",
        "VlocityDataPackType": "SObject",
        "VlocityRecordSObjectType": "OmniDataTransformItem"
    },
    {
        "CurrencyIsoCode": "USD",
        "GlobalKey": "ESRIGetAccountDetails3708068255830006",
        "InputFieldName": "Account:BillingCity",
        "IsDisabled": false,
        "IsLocked": false,
        "IsRequiredForUpsert": false,
        "IsUpsertKey": false,
        "MayEdit": true,
        "Name": "ESRIGetAccountDetails",
        "OmniDataTransformationId": {
            "Name": "ESRIGetAccountDetails",
            "VlocityDataPackType": "VlocityMatchingKeyObject",
            "VlocityMatchingRecordSourceKey": "OmniDataTransform/ESRIGetAccountDetails",
            "VlocityRecordSObjectType": "OmniDataTransform"
        },
        "OutputCreationSequence": 1,
        "OutputFieldName": "ApplicantInformation:City",
        "OutputObjectName": "json",
        "VlocityDataPackType": "SObject",
        "VlocityRecordSObjectType": "OmniDataTransformItem"
    },
    {
        "CurrencyIsoCode": "USD",
        "GlobalKey": "ESRIGetAccountDetails38269655085925947",
        "InputFieldName": "Contact:Email",
        "IsDisabled": false,
        "IsLocked": false,
        "IsRequiredForUpsert": false,
        "IsUpsertKey": false,
        "MayEdit": true,
        "Name": "ESRIGetAccountDetails",
        "OmniDataTransformationId": {
            "Name": "ESRIGetAccountDetails",
            "VlocityDataPackType": "VlocityMatchingKeyObject",
            "VlocityMatchingRecordSourceKey": "OmniDataTransform/ESRIGetAccountDetails",
            "VlocityRecordSObjectType": "OmniDataTransform"
        },
        "OutputCreationSequence": 1,
        "OutputFieldName": "ApplicantInformation:Email",
        "OutputObjectName": "json",
        "VlocityDataPackType": "SObject",
        "VlocityRecordSObjectType": "OmniDataTransformItem"
    },
    {
        "CurrencyIsoCode": "USD",
        "GlobalKey": "ESRIGetAccountDetails4312341845219634",
        "InputFieldName": "Contact:Phone",
        "IsDisabled": false,
        "IsLocked": false,
        "IsRequiredForUpsert": false,
        "IsUpsertKey": false,
        "MayEdit": true,
        "Name": "ESRIGetAccountDetails",
        "OmniDataTransformationId": {
            "Name": "ESRIGetAccountDetails",
            "VlocityDataPackType": "VlocityMatchingKeyObject",
            "VlocityMatchingRecordSourceKey": "OmniDataTransform/ESRIGetAccountDetails",
            "VlocityRecordSObjectType": "OmniDataTransform"
        },
        "OutputCreationSequence": 1,
        "OutputFieldName": "ApplicantInformation:Phone",
        "OutputObjectName": "json",
        "VlocityDataPackType": "SObject",
        "VlocityRecordSObjectType": "OmniDataTransformItem"
    },
    {
        "CurrencyIsoCode": "USD",
        "GlobalKey": "ESRIGetAccountDetails9378509373228596",
        "InputFieldName": "Account:BillingPostalCode",
        "IsDisabled": false,
        "IsLocked": false,
        "IsRequiredForUpsert": false,
        "IsUpsertKey": false,
        "MayEdit": true,
        "Name": "ESRIGetAccountDetails",
        "OmniDataTransformationId": {
            "Name": "ESRIGetAccountDetails",
            "VlocityDataPackType": "VlocityMatchingKeyObject",
            "VlocityMatchingRecordSourceKey": "OmniDataTransform/ESRIGetAccountDetails",
            "VlocityRecordSObjectType": "OmniDataTransform"
        },
        "OutputCreationSequence": 1,
        "OutputFieldName": "ApplicantInformation:PostalCode",
        "OutputObjectName": "json",
        "VlocityDataPackType": "SObject",
        "VlocityRecordSObjectType": "OmniDataTransformItem"
    },
    {
        "CurrencyIsoCode": "USD",
        "GlobalKey": "ESRIGetAccountDetails30789617123347335",
        "InputFieldName": "Account:BillingState",
        "IsDisabled": false,
        "IsLocked": false,
        "IsRequiredForUpsert": false,
        "IsUpsertKey": false,
        "MayEdit": true,
        "Name": "ESRIGetAccountDetails",
        "OmniDataTransformationId": {
            "Name": "ESRIGetAccountDetails",
            "VlocityDataPackType": "VlocityMatchingKeyObject",
            "VlocityMatchingRecordSourceKey": "OmniDataTransform/ESRIGetAccountDetails",
            "VlocityRecordSObjectType": "OmniDataTransform"
        },
        "OutputCreationSequence": 1,
        "OutputFieldName": "ApplicantInformation:State",
        "OutputObjectName": "json",
        "VlocityDataPackType": "SObject",
        "VlocityRecordSObjectType": "OmniDataTransformItem"
    },
    {
        "CurrencyIsoCode": "USD",
        "GlobalKey": "ESRIGetAccountDetails3486030297534568",
        "InputFieldName": "Account:BillingStreet",
        "IsDisabled": false,
        "IsLocked": false,
        "IsRequiredForUpsert": false,
        "IsUpsertKey": false,
        "MayEdit": true,
        "Name": "ESRIGetAccountDetails",
        "OmniDataTransformationId": {
            "Name": "ESRIGetAccountDetails",
            "VlocityDataPackType": "VlocityMatchingKeyObject",
            "VlocityMatchingRecordSourceKey": "OmniDataTransform/ESRIGetAccountDetails",
            "VlocityRecordSObjectType": "OmniDataTransform"
        },
        "OutputCreationSequence": 1,
        "OutputFieldName": "ApplicantInformation:StreetAddress",
        "OutputObjectName": "json",
        "VlocityDataPackType": "SObject",
        "VlocityRecordSObjectType": "OmniDataTransformItem"
    }
]